codecs7z/__init__.py
codecs7z/codecs7z.cp36-win_amd64.pyd
codecs7z/version.py
codecs7z-0.0.1.0.dist-info/LICENSE
codecs7z-0.0.1.0.dist-info/METADATA
codecs7z-0.0.1.0.dist-info/WHEEL
codecs7z-0.0.1.0.dist-info/top_level.txt
codecs7z-0.0.1.0.dist-info/RECORD
